automate_cpp.cp312-win_amd64.pyd
coincidence_matching.cp312-win_amd64.pyd
set_attributes.cp312-win_amd64.pyd
automate/CMakeLists.txt
automate/__init__.py
automate/automate/__init__.py
automate/automate/arg_parsing.py
automate/automate/brep.py
automate/automate/conversions.py
automate/automate/eclasses.py
automate/automate/plot_confusion_matrix.py
automate/automate/pointnet_encoder.py
automate/automate/sbgcn.py
automate/automate/util.py
automate/automate/uvnet_encoders.py
automate/cpp/automate.cpp
automate/cpp/disjointset.cpp
automate/cpp/disjointset.h
automate/cpp/eclass.cpp
automate/cpp/eclass.h
automate/cpp/lsh.cpp
automate/cpp/lsh.h
automate/cpp/part.cpp
automate/cpp/part.h
automate/include/Eigen/Cholesky
automate/include/Eigen/CholmodSupport
automate/include/Eigen/Core
automate/include/Eigen/Dense
automate/include/Eigen/Eigen
automate/include/Eigen/Eigenvalues
automate/include/Eigen/Geometry
automate/include/Eigen/Householder
automate/include/Eigen/IterativeLinearSolvers
automate/include/Eigen/Jacobi
automate/include/Eigen/KLUSupport
automate/include/Eigen/LU
automate/include/Eigen/MetisSupport
automate/include/Eigen/OrderingMethods
automate/include/Eigen/PaStiXSupport
automate/include/Eigen/PardisoSupport
automate/include/Eigen/QR
automate/include/Eigen/QtAlignedMalloc
automate/include/Eigen/SPQRSupport
automate/include/Eigen/SVD
automate/include/Eigen/Sparse
automate/include/Eigen/SparseCholesky
automate/include/Eigen/SparseCore
automate/include/Eigen/SparseLU
automate/include/Eigen/SparseQR
automate/include/Eigen/StdDeque
automate/include/Eigen/StdList
automate/include/Eigen/StdVector
automate/include/Eigen/SuperLUSupport
automate/include/Eigen/UmfPackSupport
automate/include/Eigen/src/Cholesky/LDLT.h
automate/include/Eigen/src/Cholesky/LLT.h
automate/include/Eigen/src/Cholesky/LLT_LAPACKE.h
automate/include/Eigen/src/CholmodSupport/CholmodSupport.h
automate/include/Eigen/src/Core/ArithmeticSequence.h
automate/include/Eigen/src/Core/Array.h
brepmatching-0.1.10.dist-info/LICENSE.txt
brepmatching-0.1.10.dist-info/LICENSES_OSS.txt
brepmatching-0.1.10.dist-info/METADATA
brepmatching-0.1.10.dist-info/WHEEL
brepmatching-0.1.10.dist-info/top_level.txt
brepmatching-0.1.10.dist-info/RECORD
