Metadata-Version: 2.2
Name: brepmatching
Version: 0.1.10
Summary: Topology matching using brepmatching and Femtet.
Author-email: pyfemtet <148934231+pyfemtet@users.noreply.github.com>
License: Software License Agreement (MIT License)
License-File: LICENSE.txt
License-File: LICENSES_OSS.txt
Requires-Dist: torch<3,>=2.5.1
Requires-Dist: torch-geometric<3,>=2.6.1
Requires-Dist: pytorch-lightning<3,>=2.4.0
Requires-Dist: numpy<3.0.0,>=2.0.0
Requires-Dist: pandas<3.0.0,>=2.2.3
Requires-Dist: scipy<2.0.0,>=1.14.1
Requires-Dist: scikit-learn<2.0.0,>=1.6.0
Requires-Dist: tqdm<5.0.0,>=4.66.5
Requires-Dist: dotmap<2.0.0,>=1.3.30
Requires-Dist: xxhash<4.0.0,>=3.5.0
Requires-Dist: parse<2.0.0,>=1.20.2
Requires-Dist: pywin32<307; sys_platform == "win32" and python_version < "3.13"
Requires-Dist: pywin32>=309; sys_platform == "win32" and python_version >= "3.13"
Requires-Dist: femtetutils>=1.0.0; sys_platform == "win32"
